MANIFEST.in
requirements.txt
setup.py
rqalpha_mod_hello/VERSION.txt
rqalpha_mod_hello/__init__.py
rqalpha_mod_hello/mod.py
rqalpha_mod_hello.egg-info/PKG-INFO
rqalpha_mod_hello.egg-info/SOURCES.txt
rqalpha_mod_hello.egg-info/dependency_links.txt
rqalpha_mod_hello.egg-info/not-zip-safe
rqalpha_mod_hello.egg-info/requires.txt
rqalpha_mod_hello.egg-info/top_level.txt