Metadata-Version: 1.1
Name: rqalpha-mod-hello
Version: 0.1.1
Summary: A mod for RQAlpha to say hello
Home-page: https://github.com/johnsonchak/rqalpha-mod-hello/tree/master
Author: yourname
Author-email: your@email.com
License: Apache License v2
Platform: UNKNOWN
Classifier: Programming Language :: Python
Classifier: Operating System :: Microsoft :: Windows
Classifier: Operating System :: Unix
Classifier: Programming Language :: Python :: 2.7
Classifier: Programming Language :: Python :: 3.4
Classifier: Programming Language :: Python :: 3.5
Classifier: Programming Language :: Python :: 3.6
